mock_cli/__about__.py
mock_cli/__init__.py
mock_cli/about.py
mock_cli/argv_conversion.py
mock_cli/hashing.py
mock_cli/mock_cmd.py
mock_cli/mock_cmd_state.py
mock_cli/path.py
mock_cli/pkg_resources.py
mock_cli/responses.py
mock_cli/data/__init__.py
mock_cli/data/_env-template.json
mock_cli/data/config-example.json
mock_cli/data/config-template.json
mock_cli_framework-0.8.0.dist-info/LICENSE
mock_cli_framework-0.8.0.dist-info/METADATA
mock_cli_framework-0.8.0.dist-info/WHEEL
mock_cli_framework-0.8.0.dist-info/top_level.txt
mock_cli_framework-0.8.0.dist-info/RECORD
