Metadata-Version: 2.1
Name: mock-cli-framework
Version: 0.8.0
Summary: A framework for creating stand-ins for CLI tools that pretend to be the real thing for when "the real thing" isn't suitable, such as in automated tests.
Home-page: https://github.com/zcutlip/mock-cli-framework.git
Author: Zachary Cutlip
Author-email: uid000@gmail.com
License: MIT
Requires-Python: >=3.7
License-File: LICENSE
